{"hiddenAt":"20.02.2013","waypoint":"OC12D6F","coordinates":"E 008¬∞ 25.880' N 50¬∞ 48.410'","link":"https://www.opencaching.de/viewcache.php?wp=OC12D6F","description":"So taten es die Gro√üelternDie zehn kleinen Fingerchen tasteten blind umher, gruben im Erdreich, f√ºhlten eine Wurzel, aber sie fanden nichts ‚\u20ac\u201c vorerst nicht. Es musste hier sein, er hatte es gesehen, irgendetwas war dort verborgen. Er man√∂vrierte seine inzwischen erdverschmutzten H√§nde in eine andere Position, drehte sie leicht und jetzt sp√ºrte er es. Es f√ºhlte sich k√ºhl und fest an. Er drehte es behutsam zog es wenige Millimeter zur√ºck, schob es wieder vor. Langsam, ganz langsam konnte er es im9Erdreich bewegen ‚\u20ac\u201c es begann sich zu l√∂sen.‚\u20acúWas machst du da?‚\u20ac? h√∂rte er die tiefe Stimme hinter sich. Er erschrak, so wie er erschrak, wenn er etwas Verbotenes getan hatte. Aber er hatte nichts Verbotenes getan ‚\u20ac\u201c oder etwa doch?‚\u20acúIch habe etwas entdeckt, hier an der Baumwurzel. Irgendetwas ist hier versteckt‚\u20ac?. Der Mann kniete sich neben ihn. ‚\u20acúLass mich mal sehen‚\u20ac?. Der Junge lie√ü es los und zog Hand zur√ºck. ‚\u20acúBitte Gro√üvater, lass es uns rausholen ‚\u20ac\u201c BITTE‚\u20ac?.‚\u20acúNun mal ganz ruhig‚\u20ac? sprach der √\u201eltere mit seiner sonoren Stimme. Eine Stimme, die den Jungen schon so h√§ufig beruhigt hatte, wenn er mal wieder mit dem Fahrrad gest√ºrzt war und sein Knie blutig aufgeschlagen war. Oder wenn ihn die gr√∂√üeren Jungs ge√§rgert hatten. Diese Stimme strahlte f√ºr ihn eine Ruhe aus, die nur f√ºr ihn h√∂rbar war.‚\u20acúIch werde sehen, was ich tun kann‚\u20ac? sagte der √§ltere und grub seine gro√üen H√§nde in das Erdreich. Auf den Jungen wirkte es, als wenn eine9Baggerschaufel das Loch aufriss, in dem gerade noch zwei kleine H√§nde gesteckt hatten.Der Mann machte ein paar grabende Bewegungen, schob ein wenig von der ausgehobenen Erde beiseite, kratzte mit seinen Fingern, w√ºhlte, und hob immer wieder Erde aus. Er hielt j√§h inne und zog die H√§nde langsam zur√ºck. ‚\u20acúDa, den4Rest schaffst du alleine‚\u20ac? sagte er.Ein milchig wei√üer Beh√§lter mit einer blauen Umrandung war nun deutlich zu erkennen. Der kleine sah seinen Gro√üvater mit gro√üen, ungl√§ubigen Augen an ‚\u20acúSoll ich wirklich?‚\u20ac?.Der Alte nickte l√§chelnd und der Junge meinte in seinem Mienenspiel zu erkennen, dass sein Gro√üvater irgendeine Ahnung h√§tte, was es mit dieser Kunststoffdose auf sich habe.Schlie√ülich schlossen sich die kleinen H√§nde um den Beh√§lter. Eine Art Jagdfieber ergriff ihn. Ohne den gro√üv√§terlichen Beistand h√§tte er sich wahrscheinlich nie getraut irgendetwas hier im Wald aus dem Boden zu holen.Aber jetzt wurde er von seiner Neugier angetrieben ‚\u20ac\u201c nein, er wurde geradezu von ihr getrieben.Er roch die Erde, es war ein unvergleichlicher Geruch. Erneut ber√ºhrten f√ºnf kleinen Finger das Erdreich, er konnte jetzt beidh√§ndig in das Loch greifen. Seine H√§nde umklammerten den Beh√§lter fest und zogen entschlossen daran. Endlich hielt er die Dose in seinen H√§nden.Triumphierend schaute er seinen Gro√üvater an ‚\u20acúUnd jetzt?‚\u20ac? fragte er.‚\u20acúMach es auf‚\u20ac?, forderte ihn die sonore Stimme auf, ohne das geringste Anzeichen von Hast.Der Kleine klappte die seitlich angebrachten Laschen nach oben und versuchte den Deckel zu √∂ffnen. Der r√ºhrte sich jedoch keine Millimeter, schlie√ülich packte der Junge fester zu. Er klemmte die Dose zwischen seine Knie und zog mit aller Kraft weiter.J√§h h√∂rten sie ein leises Zischen, dann sprang der Deckel so unvermittelt auf, dass der Junge erschrak. Behutsam stellte er den Beh√§lter auf den Boden und sah seinen Besch√ºtzer fragend an.‚\u20acúGreif ruhig hinein und hol alles heraus, was sich darin befindet‚\u20ac? munterte dieser ihn auf.Vorsichtig, geradezu ehrfurchtsvoll holte der Junge die Sachen aus dem Beh√§lter: Ein kleines schwarzes B√ºchlein mit rotem Buchr√ºcken, einen Schl√ºsselanh√§nger, sechs Bleistift, ein merkw√ºrdiges Schild mit einem noch merkw√ºrdigeren Aufdruck, an dessen Ende eine kleine st√§hlerne Kette durch ein Loch gezogen war. Diese Kette wiederum, war an einer kleinen Figur befestigt. Au√üerdem fand der Junge noch eine M√ºnze in dem2Beh√§lter, die ebenfalls eigenartig aussah, aber den M√ºnzen seines Gro√üvaters √§hnelte.‚\u20acúOpa, was ist das?‚\u20ac? fragte er. ‚\u20acúSchau in das5Buch‚\u20ac? antwortete der Gefragte.Der Junge folgte seiner Aufforderung und bl√§tterte das Buch auf. LOGBUCH war auf der ersten Seite handschriftlich vermerkt. Ab Seite drei folgten seltsame Eintr√§ge, die jedoch offensichtlich alle von unterschiedlichen Personen verfasst worden waren. Er erkannte es daran, dass die Schriften immer unterschiedlich waren und auch unterschiedliche Stifte verwendet wurden. Er entdeckt auch diverse Stempelabdr√ºcke und merkw√ºrdige Abk√ºrzungen, sowie eigenartige Namen.Einmal schrieb jemand, der offensichtlich Pupsi07 hie√ü ‚\u20acúTFTC‚\u20ac?, ein Stempel zeugte davon, dass ein Freiherr von Caching hier gewesen war und ein andermal war dort von der Tortellini Crew ein sehr langer Eintrag zu lesen gewesen, der damit endete, dass der Cache schnell gefunden war und man sich bedankte.√úberhaupt bedankten sich ohnehin alle ‚\u20ac\u201c f√ºr irgendetwas ‚\u20ac\u201c bei irgendjemandem.‚\u20acúAber was hat das alles zu bedeuten?‚\u20ac?.Der √\u201eltere st√ºtze seine linke Hand auf den Boden und drehte seinen K√∂rper, so dass er schlie√ülich neben dem Jungen auf dem Boden sa√ü.‚\u20acúNun, dass ist eine l√§ngere Geschichte, setzt dich neben mich‚\u20ac?.Nachdem der Junge der Aufforderung gefolgt war, begann die klangvolle Stimme des Gro√üvaters:‚\u20acúGib acht! Ich habe dir doch schon erz√§hlt, dass ich mich gelegentlich mit anderen Sammlern treffe, um meine M√ºnzen zu tauschen ‚\u20ac\u201c die, die ich in meinem Arbeitszimmer in den sch√∂nen Lederalben aufbewahre‚\u20ac?. Der Junge nickte und sah seinen Gro√üvater mit gro√üen Augen an, die eine Aufforderung zum weitersprechen formulierten, so, wie ein Verdurstender nach einer Wasserflasche rufen w√ºrde.‚\u20acúFr√ºher haben wir diese M√ºnzen auch schon getauscht, aber nicht nur das ‚\u20ac\u201c wir haben unsere M√ºnzen auch reisen lassen‚\u20ac? fuhr er mit seiner sch√∂nen Bassstimme fort.Der Blick des Alten war ein wenig entr√ºckt, er schien in die Ferne zu sehen, aber um sie herum standen √ºberall B√§ume es gab hier gar keine Ferne.‚\u20acúWir hatten damals ein Spiel, dass hie√ü Geocaching. An sch√∂nen0Orten versteckten wir unsere sogenannten Container. Das waren manchmal kleine, manchmal aber auch gro√üe Kunststoffdosen oder Metallbeh√§lter. In einsamen W√§ldern gab es sogar richtig gro√üe Kisten. In allen Beh√§ltern waren Logb√ºcher, so wie dieses hier, deponiert‚\u20ac?. Mittlerweile hatte der Alte den Kopf leicht angehoben, so als wolle er die Ferne nun in den Wipfeln der B√§ume suchen.‚\u20acúWir trugen uns in diese B√ºcher ein, nahmen etwas aus der Kiste, legten etwas anderes daf√ºr hinein und deponierten unsere M√ºnzen‚\u20ac? sagte er, wobei seine Stimme inzwischen die Ferne erreicht zu haben schien, die seine Augen suchten.‚\u20acúViele Menschen suchten und fanden diese Beh√§lter, verewigten sich in den Logb√ºchern und tauschten Gegenst√§nde. Wenn wir eine Dose gefunden hatten, gingen wir nach Hause und setzten uns als erstes an unsere Computer. Wir trugen unseren Fund auf einer Webseite ein, auf der man auch nachsehen konnte, wo die Beh√§lter √ºberall versteckt waren‚\u20ac?.7Inzwischen schienen auch die Augen der Stimme gefolgt zu sein und hatten offensichtlich ihr Ziel erreicht - der alte Mann war in seiner Vergangenheit weit zur√ºck gereist.‚\u20acúDas Ganze war ein Suchspiel, wir ver√∂ffentlichten Koordinaten im Internet, die wir mit GPS Ger√§ten aufsuchten. Dort begannen wir dann mit der Suche nach den Dosen‚\u20ac?.‚\u20acúUnd weiter?‚\u20ac? fragte der Junge neugierig, der inzwischen von der Geschichte seines Gro√üvaters gefesselt war.‚\u20acúNun, es wurden immer mehr Menschen, die diese Beh√§lter versteckten und suchten. Im Wald, in der Stadt, an der Autobahn, auf Br√ºcken. Einige der Verstecke waren nur zu erreichen, wenn man irgendwo hinauf kletterte, oder sich abseilte‚\u20ac?.Der Junge bekam gro√üe Augen ‚\u20acúToll!‚\u20ac? rief er ganz leise, weiter der Geschichte des Gro√üvaters folgend.‚\u20acúJa, toll ‚\u20ac\u201c dass war es in der Tat‚\u20ac? antwortete dieser und fuhr dann fort: ‚\u20acúAber schlie√ülich suchten und versteckten unglaublich viele Menschen diese Beh√§lter. Am Ende waren es einfach zu viele. So kam es immer h√§ufiger zu Problemen mit anderen Mitmenschen und Beh√∂rden. Schlie√ülich kam es sogar zu Polizeieins√§tzen, weil besorgte Anwohner Angst hatten, dass die Beh√§lter gef√§hrlich sein k√∂nnten. Und auch in den W√§ldern kam es h√§ufiger zu4Problemen. B√§ume wurden besch√§digt, Tiere wurden gest√∂rt, einige Mitspieler verhielten sich der Natur gegen√ºber respektlos. Schlie√ülich passierte, was passieren musste ‚\u20ac\u201c unser Spiel wurde verboten‚\u20ac?. Seine Stimme war bei den letzten Worten merklich leiser geworden.‚\u20acúUnd dann habt ihr aufgeh√∂rt es zu spielen‚\u20ac? f√ºhrte der Junge den Satz fort. ‚\u20acúOh nein‚\u20ac?, fiel der √\u201eltere ein, ‚\u20acúnicht sofort. Wir hielten das Verbot f√ºr einen Spa√ü. Als dann aber die ersten von uns m√§chtigen √\u201erger mit der Polizei und den Beh√∂rden bekamen, wurden wir vorsichtiger. Nachdem aber schlie√ülich tats√§chlich einige Mitspieler verklagt wurden und hohe Strafen zahlen mussten, weil sie widerrechtlich Privatbesitz betreten hatten und zus√§tzlich noch gegen das Spielverbot verstie√üen, wurden wir immer weniger Spieler‚\u20ac?. Seine Stimme verlor noch mehr an Lautst√§rke und war auch nicht mehr so fest, wie es der Junge gewohnt war.‚\u20acúSchlie√ülich mussten sogar Leute ins Gef√§ngnis, weil sie die Strafen nicht zahlen konnten, oder einfach weil sie sich gegen die Beh√∂rden auflehnten. Ab diesem Zeitpunkt brach das Spiel in sich zusammen. Die meisten der Beh√§lter wurden von den Versteckern eingesammelt, oder wurden irgendwann zuf√§llig von irgendjemandem gefunden und abgegeben oder in den M√ºll geworfen‚\u20ac?. Der alte Mann schien zu schrumpfen, er r√§usperte sich kurz, dann sah er den kleinen unverwandt an und sagte fast fl√ºsternd, eins muss ich Dir noch sagen: ‚\u20acúDas Spiel war zu Ende, wir alle waren die Verlierer‚\u20ac?.Stille ‚\u20ac\u201c nur das Zwitschern der V√∂gel war zu h√∂ren, ein Specht, weit entfernt ging seiner Arbeit nach und rammte seinen Schnabel unaufh√∂rlich in einen Baum. Millimeter um1 Millimeter trieb er ihn weiter voran, so wie der kleine Junge es mit seiner Hand getan hatte, als er etwas an einer Baumwurzel sah und es aus dem Erdreich grub.‚\u20acúHast du damals auch aufgeh√∂rt?‚\u20ac? fragte der Kleine pl√∂tzlich. ‚\u20acúNat√ºrlich‚\u20ac? erwiderte der Alte m√ºde. ‚\u20acúIch habe damals, wie alle anderen auch, dass Spiel f√ºr mich beendet.Das Einzige was von diesem Spiel √ºbrig geblieben ist, sind die Menschen, die es damals spielten. Sieben von ihnen treffe ich heute gelegentlich noch zum M√ºnztausch, dann erz√§hlen wir uns Geschichten von fr√ºher‚\u20ac?.Der Alte reichte dem Jungen den7Stift aus dem Beh√§lter und forderte ihn auf: ‚\u20acúTrag dich in das B√ºchlein ein, schreib einfach, dass du hier warst und bedanke dich‚\u20ac?.‚\u20acúWarum? Das Spiel wird doch l√§ngst nicht mehr gespielt‚\u20ac?, fragte er.Er blickte dem Kleinen fest in die Augen, ein leichter Glanz war in ihnen zu sehen. Seine Mundwinkel zogen sich leicht nach oben und der Gro√üvater sagte mit verschw√∂rerisch fl√ºsternder Stimme: ‚\u20acúDas Spiel ist verboten und wird nicht mehr gespielt ‚\u20ac\u201c offiziell jedenfalls. Aber es gibt wieder einige Spieler. Sie verstehen es mittlerweile, dass Spiel auf eine Art zu spielen, die andere nicht bel√§stigt, den Beteiligten aber trotzdem viel Freude bereitet‚\u20ac?. Seitdem gibt es auch keine Probleme mehr. Er zwinkerte seinem Enkel zu. Dann warf er einen Blick in das Logbuch ‚\u20acúDer letzte Eintrag liegt bereits viele Jahre zur√ºck. Lass uns alles wieder gut verstecken, in vier Wochen werden wir nachsehen, ob noch jemand anderes3diese Dose gefunden hat ‚\u20ac\u201c ich werde die Information verbreiten, dass hier immer noch ein Geocache liegt‚\u20ac?.Sie legten alle neun Gegenst√§nde zur√ºck in die Dose und verstauten sie wieder gut am Fu√üe des9Baumes. Dann tarnten sie das Versteck mit Bl√§ttern und zwei kleinen √\u201esten.Schlie√ülich stand der √\u201eltere auf und reichte seinem Enkel die Hand, schweigend verlie√üen sie den Wald in exakt der Richtung, in die der Gro√üvater noch vor kurzem gesehen hatte, als er in seine6Gedanken versunken war.In der Hoffnung, dass dies einfach eine Geschichte bleibt, w√ºnsche ich viel Spa√ü beim Knobeln und der Dosensuche - die MiniMaus. Ach ja: Und wer Fehler findet darf sie behalten! Mein Dank geht an Dithmarscher, Don und watz. Ihr wisst schon... Und... Wer nen Checker braucht, dem spendier ich einen ¬© MiniMaus71, Opencaching.de, CC BY-NC-ND, Stand: 07.05.2018;alle Logeintr√§ge ¬© jeweiliger Autor","tips":"Jraa Qh orv tro√ºpxgre Unyghat nhserpug fgrufg, qnaa ovfg Qh evpugvt!","caseType":"nano","difficulty":3.5,"condition":"ok","name":"Zeitgeschichte(n) #4 von MiniMaus71","cacheType":"R√§tselcache","terrain":1.5,"logs":[{"date":" 06.03.2013 ","person":"crisb ","message":" Wieder so ein typisches Minimaus-R√§tsel, das auf den ersten Blick einfach nur aus viel zu viel Text besteht [;)] Doch bei n√§herem Hinschauen stellte sich heraus, dass mir irgendwas bekannt vorkam und so war der richtige Ansatz schnell . Dann scheiterte es blo√ü noch an der Unordnung. Schlie√ülich zeigten sich aber irgendwann Koordinaten [:D]Heute ging es bei herrlichem Wetter ins Zielgebiet. Nach kurzer Orientierung war dann klar wie der Hint zu verstehen ist. Witzige Sache [;)]Danke f√ºr den Cache! Hoffen wir mal, dass es so nicht verlaufen wird...Gru√ü crisb"}],"descriptionSnippet":"","status":"kann gesucht werden"}