{"hiddenAt":"22.07.2016","waypoint":"OC1316D","coordinates":"E 007° 50.960' N 47° 59.758'","link":"https://www.opencaching.de/viewcache.php?wp=OC1316D","description":"Die Legende des Kegelgeistes des Schlossberges:Einst wurde in Kriegszeiten auf dem Freiburger Schlossberg eine kostbare Monstranz aus dem Münsterschatz vergraben, die man aber bis heute nicht wieder fand. Viele haben schon nach ihr gesucht. Endlich stieß einer der Schatzgräber auf eine mit Zement übergossene Platte. Da wurden ihm seine weiteren Nachgrabungen untersagt. In einer mondhellen Nacht suchte einst ein Mann nach vermeintlichen Schätzen an der Burghalde. Plötzlich erschreckte ihn ein Flimmern und Schimmern durch Zweige und Gemäuer. Er schlich näher und sah in eine versteckte Grotte den Zwergkönig auf goldener Karosse einfahren mit vielem Gefolge. Fröhlich lagerte sich die Gesellschaft in ihren goldstrotzenden Kleidern mit den weißen Kleidern darüber um einen goldenen Tisch, wo sie mit Edelsteinen besetzte Becher kreisen ließen. Plötzlich hörte man ein leises Wimmern. Bald aber donnerte und rollte es vom Schlossberg her, und eine laute Stimme rief: Setzt meine Kegel auf!\" Acht geisterbleiche Gesellen mit weißen Pluderhosen und roten Mützen begannen darauf unter den Bäumen ein wildes Gelage, während die Zwerglein ein volles, goldenes Kegelspiel aus der Tiefe herbeischleppten. Vergeblich mühte sich der Kegelgeist bis zum Morgengrauen ab, den neunten Kegel zu fällen, nachdem seine Gesellen achte geworfen hatten. Ohne Erfolg und unerlöst musste, er mit dem scheidenden Morgen von dannen ziehen, bis sich doch einmal einer findet, der ihm den neunten\" Kegel schiebt. Der Schatzgräber aber war vor Schreck ob des Geschauten ganz sinnlos geworden, stürzte einen Abhang hinunter und fand dabei einen kläglichen Tod.Stelle dir vor du bist Hobby-Schatzsucher. Du kommst nach Freiburg und hörst von der Legende des Kegelgeistes. Du beschließt dich auf die Suche zu machen. Du machst ein paar Leute ausfindig, die den Schatz ebenfalls gesucht haben:Bertold SchwarzFritz Sebastian MeierHeinrich DreherChristian Eduard SchneiderSie geben dir jeweils einen Hinweis auf das Final...Station 1: Du startest bei N47°59.759 E007°50.960. Dort wirst du den Namen eines Schatzsuchers finden. in der Nähe befinden sich zwei Jahreszahlen. Dort musst du die kleinere Jahreszahl von der größeren abziehen. Die Differenz ist AStation 2: Jetzt musst du zu N47°59.680 E007°51.180. Dort findest du Initialien von einem weiteren Schatzsucher. Addiere die zwei Zahlen, die du auf dem Boden findest. Dies sei B.Station 3: Bei N47°59.630 E007°51.276 findest du die Initialien eines Schatzsuchers. Sie sind umgeben von einer Jahreszahl. Die Quersumme der Zahl ist C.Station 4:Eine erneute Suche nach Initialien bei N47°59.619 E007°51.373.Du musst die ganzen Raute zählen (keine halben). Das ist D.Vorfinale: findest du bei N47°59.601 E007°51.376. Suche eine kleine Box, der Rest erklärt sich anschließend von selbst.© AngellGeoTeam, Opencaching.de, CC BY-NC-ND, Stand: 07.05.2018;alle Logeinträge © jeweiliger Autor","tips":"Orv Rsrh (Ibesvanyr + Svany)   ","caseType":"klein","difficulty":2,"condition":"ok","name":"Der Kegelgeist vom Schlossberg von AngellGeoTeam","cacheType":"Multicache","terrain":3,"logs":[{"date":" 21.07.2017 ","person":"AngellGeoTeam ","message":" HinweisDer Cache wurde erneuert! "}],"descriptionSnippet":"Basierend auf der Legende des Kegelgeistes vom Schlossberg mit mehreren Stationen und ein bisschen Wandern! ","status":"kann gesucht werden"}