{"hiddenAt":"04.10.2010","waypoint":"OCB2D4","coordinates":"E 013° 47.940' N 50° 48.053'","link":"https://www.opencaching.de/viewcache.php?wp=OCB2D4","description":"Ein technisches Denkmal, eine ganze Kursächsische Postmeilensäule.Eine Kursächsische Wegstunde, eine halbe Meile, entspricht 4,531 Km.Vermessen wurden die Poststraßen mit einem Messwagen bzw.Meilenwagen. Das ist ein geometrischer Wagen, ein mit einem Zählwerk ausgestattete Kutsche, die noch  zusätzlich eine Schubmesskarre mit Zählwerk mitführte.Es gibt ganze Meilensäulen, halbe Meilensäulen und viertel Meilensäulen. Die Säulen mußten die Bürger bezahlen.Quelle Lichtbild: Wolf.GangLogbedingungen.Denkerst gar nicht daran, andere Logbedingungen anzuwenden als diese. Dugibst mir dann den Anlass deinen Log zu löschen!Mit deinemOnline-Log füge dein Beweisfoto hinzu, aufdem der virtuelle Cache und der erbrachte Beweis, dassdas Bild für diesen Cache aufgenommen wurde,gut zu erkennen sind.AlsBeweis ist auf dem Lichtbild mit abgebildet, z.B. ein Finger oder einGPS-Gerät oder Beteiligte oder andere Dinge die man in das Bildhalten kann, wie z.B. Stift oder Maskottchen. Siehe Logbeispielfoto.© Wolf.Gang, Opencaching.de, CC BY-NC-ND, Stand: 24.04.2018;alle Logeinträge © jeweiliger Autor","tips":"","caseType":"kein Behälter","difficulty":1,"condition":"ok","name":"Postmeilensäule in Bärenstein von Wolf.Gang","cacheType":"virtueller Cache","terrain":1,"logs":[{"date":" 15.04.2018 16:24 ","person":"93Roma ","message":" Auf unserer heutigen Bärensteiner Sonntagsrund kamen wir natürlich auch hier vorbei. Danke fürs herführen ☺ "},{"date":" 05.09.2017 ","person":"tillit23 ","message":" Auf Durchreise bei einer kombinierten Geocaching"},{"date":" 02.07.2017 12:06 ","person":"jeje810~ccr35 ","message":" 12:06 Schöne Postsäule in Bärenstein, die wir uns heut ausgesucht haben."},{"date":" 14.11.2016 18:42 ","person":"mutzls0407 ","message":" "},{"date":" 10.07.2016 ","person":"wienja ","message":" Meine Cacherunde führte mich auch zur Postmeilensäule in Bärenstein.Danke fürs herführen sagt wienja"},{"date":" 13.09.2015 15:00 ","person":"fedato ","message":" Wir waren hier nach einer schönen Bärensteiner Sonntagsrunde...ist das der Abschluss für heute..."},{"date":" 04.05.2015 13:56 ","person":"Fraxel ","message":" Heute angeschaut, mit unserer kleinen Nachwuchscacherin in Ihrem \"Mobil\".TFTC"},{"date":" 02.01.2015 ","person":"MrMittens ","message":" Mein erster "},{"date":" 28.03.2011 ","person":"gum4711 ","message":" Auf einer kleinen Cacherunde durchs Osterzgebirge auch in Bärenstein vorbeigefahren.TFTC."},{"date":" 08.11.2010 ","person":"ErWiWo ","message":" Heute zum Fototermin vorbeigekommen. TFTC"},{"date":" 22.10.2010 ","person":"blutiger.engel87 ","message":" gut , schnell geloggtdanke sagt blutiger.engel87 "}],"descriptionSnippet":"Virtueller Cache mit Logbedingungen.","status":"kann gesucht werden"}