{"hiddenAt":"11.07.2012","waypoint":"OCE7A1","coordinates":"E 013° 17.117' N 50° 35.016'","link":"https://www.opencaching.de/viewcache.php?wp=OCE7A1","description":"Das AntonsEck ist mit 780m üNN der höchste Punkt von Rübenau. Von hier aus kann man fast ganz Rübenau überblicken. Der Cache ist ohne große Probleme zu finden und soll die schöne Aussicht auf das weitverzweigte Gebirgsdorf Rübenau bzw. Kallich in Tschechien zeigen. Auf Grund des letzten Eintrags von MiBa das der Cache nicht gefunden wurde, habe nachgesehen und noch alles vor Ort aufgefunden. Der Cache ist also OK und eigentlich leicht zu finden.© do1cs, Opencaching.de, CC BY-NC-ND, Stand: 24.04.2018;alle Logeinträge © jeweiliger Autor","tips":"","caseType":"normal","difficulty":1.5,"condition":"ok","name":"AntonsEck von do1cs","cacheType":"Drive-In-Cache","terrain":1.5,"logs":[{"date":" 07.01.2018 14:47 ","person":"elisabeth.115 ","message":" Bei blödem Nieselregen warten wir uns aus dem warmen Stäbchen.. ..und fanden das Döschen TFTC"},{"date":" 02.12.2017 10:10 ","person":"RICCCO363 ","message":" Einen wunderschönen recht herzlichen Dank für das hierher locken danke"},{"date":" 05.07.2016 16:39 ","person":"geo-2015 ","message":" Schöne Aussicht.  Danke"},{"date":" 27.07.2015 ","person":"kreativetante ","message":" "},{"date":" 10.07.2015 16:58 ","person":"kreativetante ","message":" Schöne Aussicht schnell .  Danke fürs legen und pflegen. "},{"date":" 26.06.2015 19:25 ","person":"ASAR885 ","message":" Sehr schöne Aussicht, danke fürs herlocken."},{"date":" 02.10.2013 ","person":"issegal ","message":" Zum Tagesausklang waren wir noch Drachensteigen auf der Wiese hinterm Kriegwald. Es fand sich auch noch Zeit zum Suchen dieses Caches."},{"date":" 02.10.2013 ","person":"migrarebarathrum ","message":" Auf dem Rückweg vom Natschungtal diese Dose entdeckt."},{"date":" 03.08.2013 ","person":"RealNebulus ","message":" Schöner Ort mit interessanter Geschichte.Danke sagt RealNebulus"},{"date":" 19.08.2012 ","person":"migrarebarathrum ","message":" Hinweiswir waren das 6te mal da! der Ort ist schön wir haben aber kein cache ! MiBa"},{"date":" 24.07.2012 ","person":"rübenauer ","message":" Eine herrliche Sicht übers Erzgebirge."}],"descriptionSnippet":"","status":"kann gesucht werden"}