{"hiddenAt":"12.02.2018","waypoint":"OC14543","coordinates":"E 007° 32.236' N 51° 29.775'","link":"https://www.opencaching.de/viewcache.php?wp=OC14543","description":"Die herrliche Jesus-Statue  Hallo. Der Cache befindet sich auf dem kleinen Hügel bei der Jesus-Statue am Parkplatz des Kindergartens und man MUSS auf den Hügel hoch gehen!!!© FoundBoy, Opencaching.de, CC BY-NC-ND, Stand: 07.05.2018;alle Logeinträge © jeweiliger Autor","tips":"","caseType":"normal","difficulty":1.5,"condition":"Cache benötigt Wartung","name":"Die herrliche Jesus-Statue von FoundBoy","cacheType":"normaler Cache","terrain":2,"logs":["dogesu / 17.02.2018 / momentan nicht verfügbarEiner Meldung zufolge ist keine Dose vorhanden. Der Owner sollte hier dringend vor Ort erscheinen und die Lage überprüfen; bis dahin setze ich den Status auf \"Momentan nicht verfügbar\". Sobald der Cache gewartet wurde, kann ihn der Owner wieder selbstständig durch ein \"kann gesucht werden\"-Log aktivieren.Bei Unklarheiten oder Fragen kannst du gerne mich oder das Team kontaktieren.dogesu (OC-Support)","HWR-Info / 13.02.2018 / gefundenFTF - 10:00 Uhr "],"descriptionSnippet":"Ein netter Cache am Parkplatz des Kindergartens","status":"momentan nicht verfügbar"}