{"hiddenAt":"18.02.2018","waypoint":"OC1456D","coordinates":"E 013° 07.533' N 48° 44.245'","link":"https://www.opencaching.de/viewcache.php?wp=OC1456D","description":"Am besten parkt ihr bei der Bushaltestelle, ihr habt hier einen tollen Blick auf den Brotjackelriegel(mit Funkturm) und den vorderen Bay. Wald. Folgt dann dem Radweg. Den Cache geht ihr am besten \"hinten rum\" an oder \"von unten\"© zuchzwerg, Opencaching.de, CC BY-NC-ND, Stand: 07.05.2018;alle Logeinträge © jeweiliger Autor","tips":"Va ubuyrz Onhzfghzcs","caseType":"klein","difficulty":3,"condition":"ok","name":"Der Stein der Weisen von zuchzwerg","cacheType":"normaler Cache","terrain":3,"logs":[],"descriptionSnippet":"Kleiner Cache mit Tauschgegenständen","status":"kann gesucht werden"}