{"hiddenAt":"05.11.2017","waypoint":"OC14164","coordinates":"E 008° 48.300' N 53° 04.666'","link":"https://www.opencaching.de/viewcache.php?wp=OC14164","description":"Der Cache liegt nicht an den angegeben Koords | The mystery isn't hide at the given coordinatesZwei Retro GamesMoin,ihr fragt euch welche?Die wahrscheinlich einfachsten: Snake und eine Abwandlung von Pong (bzw. Brick) Snake:Ich glaube dieses Spiel kennt jeder. Du steuerst mit den Pfeiltasten und dein Ziel sind 75 Punkte.Hier geht es zum Spiel: SnakeHier geht es zum Original Produnkt: OriginalWem das spiel Spaß macht, kann hier spielen. (Achtung ihr beommt keine Koords am Ende!!!)Pong:Sammel mit dem Ball Tradis und Multis um Punkte zu bekommen. dein Ziel sind 250 Punkte. Starten kannst du mit Drücken des Leerzeichens.Hier geht es zum Spiel: Pong (Brick)Wem das spiel Spaß macht, kann hier spielen. (Achtung ihr beommt keine Koords am Ende!!!)Viel Spaß wünschtcapoaira© capoaira, Opencaching.de, CC BY-NC-ND, Stand: 07.05.2018;alle Logeinträge © jeweiliger Autor","tips":"[Rätsel:] Orv Fanxr vfg rvar Fpber iba 75 aögvt orv Cbat oenhpug vue 250. Ivry Fcnß![Final:] Nhpu rue Ergeb (G....)","caseType":"kein Behälter","difficulty":4,"condition":"ok","name":"Zwei Retro Games von capoaira","cacheType":"Rätselcache","terrain":1.5,"logs":[],"descriptionSnippet":"Da ihr kein Rätsel lösen müsst, finde ich, dass dies kein Mystery ist.","status":"kann gesucht werden"}