{"hiddenAt":"03.01.2016","waypoint":"OC12956","coordinates":"E 007° 43.000' N 51° 56.000'","link":"https://www.opencaching.de/viewcache.php?wp=OC12956","description":"Die Lösung des Rätsel findest Du im Cachenamen,© Dimer, Opencaching.de, CC BY-NC-ND, Stand: 07.05.2018;alle Logeinträge © jeweiliger Autor","tips":"","caseType":"mikro","difficulty":2.5,"condition":"ok","name":"Paula - Ursmar von Dimer","cacheType":"Rätselcache","terrain":2,"logs":[{"date":" 27.01.2018 ","person":"Dimer ","message":" kann gesucht werdenHabe heute einen Geochecker eingefügt."},{"date":" 10.02.2016 ","person":"nobwo ","message":" Auf unserer Tour nach Wolbeck sollte auch dieses Mystery noch mitgenommen werden. Die \"Mutter\" der Reihe war auch alserste gelöst, so dass nun nur noch eine Dose offen ist.Danke für das Auslegen und den schnellen Fund."},{"date":" 06.01.2016 ","person":"Team Z14 ","message":" Nach dem das Rätsel gelöst war, stand heute der Outdoorteil an. Die Dose gesucht,  und geloggt. Danke für den Cache"}],"descriptionSnippet":"","status":"kann gesucht werden"}