{"hiddenAt":"25.10.2017","waypoint":"OC13F94","coordinates":"E 009° 39.405' N 54° 49.306'","link":"https://www.opencaching.de/viewcache.php?wp=OC13F94","description":"Kein Cache ist es wert, sich oder andere in Gefahr zu bringen!Blauer Abschnitt 24.8 VIRTUALWas ist der \"Limes balticus\"?Die zweite Ziffer im Text auf der Infotafel: \"Die Ostsse hat...\u201c ist die Zahl für den Bonuscode: 24A=?und das Passwort, um diesen Cache zu loggen. © Le Dompteur, Opencaching.de, CC BY-NC-ND, Stand: 07.05.2018;alle Logeinträge © jeweiliger Autor","tips":"\"Qvr Bfgffr ung rvar Jnffresyäpur iba 4?6.000 xz²...\"","caseType":"kein Behälter","difficulty":1,"condition":"ok","name":"Limes balticus 24.8 von Le Dompteur","cacheType":"virtueller Cache","terrain":1.5,"logs":[{"date":" 22.04.2018 ","person":"DiSiEmNi ","message":" So direkt vor der Wohndose konnte der gut erledigt werden. Die restlichen werde ich wohl bei besserem Wetter mal besuchen."},{"date":" 29.12.2017 11:30 ","person":"Pinnie und Pueppie ","message":" Cache braucht wohl so schnell keine Wartung.Lustige Idee."}],"descriptionSnippet":"Trail zwischen den Fjorden","status":"kann gesucht werden"}