{"hiddenAt":"11.04.2017","waypoint":"OC13911","coordinates":"E 009° 25.029' N 48° 42.259'","link":"https://www.opencaching.de/viewcache.php?wp=OC13911","description":"Bruwatzel, der BruckenwasenklabauterboldEin Rätsel -Cache erstellt durch Glücksritter.CGGFinde das Versteck des BruwatzelsStart (Parkplatz) Bruckenwasen (unter der B10)\tN 48°42.259 \tE 9°25.029Kinderfragen (K) ; Fragen für Andere (A)-Station 1 \tN 48°42.354 E9°25.005 K: Wieviele Wellen siehst Du hier?        \t\t\tA:___ A: Wieviele Zyklopen stecken in der Böschung ?    \tB:___\u2026..........................................................................................................................-Station 2    \tK: N48°42.(A-2)21      E9°25.01(3+A)\t\tA: N48°42.(B-1)21      E9°25.01(B+2x2) K: Wieviele Stufen hat diese Uhr?\t\t\t\tC:___      Was ist die Zahl des Löwen?\t\t\t\tD:___ A: Wieviel Worte macht die Steinstele?\t\t\tE:___      Wieviele \u201eZ\u201c stecken im Text?\t\t\t\tF:___\u2026..........................................................................................................................-Station 3\tK: N48°42.(7-C)2A\tE9°25.(A-D)2(A+C-2)\t\tA: N48°42.F(E+2xF)  E9°25.(6xE+B+F) K: Wieviele Bullaugen schauen aufs Blau ? \t\tG:___ A:  Wieviele Schritte braucht ein Erwachsener,       um um das Blau herumzugehen? >72: H ist 9\t\t\t\t\t     <72: H ist 5           H:___\u2026...........................................................................................................................-Station 4\tK: N48°42.(G-3)G(3+C)  E9°25.(G-4)2C\t\tA: N48°42.(Hx28+5)\t      E9°25.(H+F)(E:5)K: Wieviele Hunde sind immer auf der Wiese ?              N:___ A: Wie lange ist der Eisenweg ?     >1,6 km: I ist 2    \tI:___                                                           <1,6 km: I ist 5\u2026..........................................................................................................................-Station 5\tK: N48°42.2(1+N)(A-3)  E9°25.1(N+2) (2xC)\t\tE: N48°42.(52xI+F)\t   E9°25.(Ix30+E+B+3) K: Wieviele Metallträger kannst Du       beim Überqueren des Flusses überspringen ?\t\tJ:___     Wieviele Kilometer sind es von      hier nach Nürtingen mit dem Fahrrad?\t\tK:___ A: Wann wurde der Erfinder       dieser technischen Errungenschaft geboren?    \tL:___      Wieviel Liter werden in einer Sekunde gehoben?\tM:___Das Versteck des Bruwatzel findest du hier:\tK: N48°42.(J+K)(J-K+1) E9°25.(J+2)(C-1)          A: N48°42.(L+M-18)  E9°25.(3xM-H+E/10)© Glücksritter.CGG, Opencaching.de, CC BY-NC-ND, Stand: 07.05.2018;alle Logeinträge © jeweiliger Autor","tips":"Irefpuyüffrygre Uvajrvf (EBG13):                                                                          N O P Q R S T U V  W  X Y Z                                                                          A B C D E F G H IJ K L MDrei Strich Steuerbord unten____ ______ _________  _____","caseType":"normal","difficulty":1.5,"condition":"ok","name":"Bruwatzel, der Bruckenwasenklabauterbold von Glücksritter.CGG","cacheType":"Rätselcache","terrain":1,"logs":[],"descriptionSnippet":"","status":"kann gesucht werden"}